README.md
setup.py
blockchain_spark.egg-info/PKG-INFO
blockchain_spark.egg-info/SOURCES.txt
blockchain_spark.egg-info/dependency_links.txt
blockchain_spark.egg-info/requires.txt
blockchain_spark.egg-info/top_level.txt
spark3/__init__.py
spark3/ethereum.py
spark3/transfomer.py
test/__init__.py
test/resources/__init__.py
test/spark3/__init__.py
test/spark3/ethereum_test.py
test/spark3/pyspark_test.py