Metadata-Version: 2.1
Name: blockchain-spark
Version: 0.2.2
Summary: Spark extension utils for blockchain
Home-page: https://github.com/tellery/blockchain-spark
Author: songv
Author-email: songwei@iftech.io
License: UNKNOWN
Project-URL: Bug Reports, https://github.com/tellery/blockchain-spark/issues
Project-URL: Source, https://github.com/tellery/blockchain-spark
Keywords: web3,pandas
Platform: UNKNOWN
Classifier: Development Status :: 5 - Production/Stable
Classifier: Intended Audience :: Developers
Classifier: License :: OSI Approved :: MIT License
Classifier: Programming Language :: Python :: 3
Classifier: Programming Language :: Python :: 3.6
Classifier: Programming Language :: Python :: 3.7
Classifier: Programming Language :: Python :: 3.8
Classifier: Programming Language :: Python :: 3.9
Requires-Python: >=3.6,<4
Provides-Extra: pyspark
